igeorgiev/__init__.py
igeorgiev-0.0.1.dist-info/LICENSE
igeorgiev-0.0.1.dist-info/METADATA
igeorgiev-0.0.1.dist-info/WHEEL
igeorgiev-0.0.1.dist-info/top_level.txt
igeorgiev-0.0.1.dist-info/RECORD
