Metadata-Version: 2.1
Name: igeorgiev
Version: 0.0.1
Summary: Root Python library package
Author-email: Ivan Georgiev <ivan.georgiev@gmail.com>
License: MIT License        
Project-URL: Homepage, https://github.com/ivangeorgiev/igpy
Project-URL: Bug Tracker, https://github.com/ivangeorgiev/igpy/issues
Classifier: Programming Language :: Python :: 3
Classifier: License :: OSI Approved :: MIT License
Classifier: Operating System :: OS Independent
Requires-Python: >=3.7
License-File: LICENSE
